CHANGELOG
LICENSE
MANIFEST.in
README.md
requirements.txt
setup.cfg
setup.py
.eggs/flake8-4.0.1-py3.10.egg/EGG-INFO/LICENSE
.eggs/flake8-4.0.1-py3.10.egg/flake8/__init__.py
.eggs/flake8-4.0.1-py3.10.egg/flake8/__main__.py
.eggs/flake8-4.0.1-py3.10.egg/flake8/_compat.py
.eggs/flake8-4.0.1-py3.10.egg/flake8/checker.py
.eggs/flake8-4.0.1-py3.10.egg/flake8/defaults.py
.eggs/flake8-4.0.1-py3.10.egg/flake8/exceptions.py
.eggs/flake8-4.0.1-py3.10.egg/flake8/processor.py
.eggs/flake8-4.0.1-py3.10.egg/flake8/statistics.py
.eggs/flake8-4.0.1-py3.10.egg/flake8/style_guide.py
.eggs/flake8-4.0.1-py3.10.egg/flake8/utils.py
.eggs/flake8-4.0.1-py3.10.egg/flake8/api/__init__.py
.eggs/flake8-4.0.1-py3.10.egg/flake8/api/legacy.py
.eggs/flake8-4.0.1-py3.10.egg/flake8/formatting/__init__.py
.eggs/flake8-4.0.1-py3.10.egg/flake8/formatting/base.py
.eggs/flake8-4.0.1-py3.10.egg/flake8/formatting/default.py
.eggs/flake8-4.0.1-py3.10.egg/flake8/main/__init__.py
.eggs/flake8-4.0.1-py3.10.egg/flake8/main/application.py
.eggs/flake8-4.0.1-py3.10.egg/flake8/main/cli.py
.eggs/flake8-4.0.1-py3.10.egg/flake8/main/debug.py
.eggs/flake8-4.0.1-py3.10.egg/flake8/main/options.py
.eggs/flake8-4.0.1-py3.10.egg/flake8/options/__init__.py
.eggs/flake8-4.0.1-py3.10.egg/flake8/options/aggregator.py
.eggs/flake8-4.0.1-py3.10.egg/flake8/options/config.py
.eggs/flake8-4.0.1-py3.10.egg/flake8/options/manager.py
.eggs/flake8-4.0.1-py3.10.egg/flake8/plugins/__init__.py
.eggs/flake8-4.0.1-py3.10.egg/flake8/plugins/manager.py
.eggs/flake8-4.0.1-py3.10.egg/flake8/plugins/pyflakes.py
.eggs/mccabe-0.6.1-py3.10.egg/mccabe.py
.eggs/pycodestyle-2.8.0-py3.10.egg/pycodestyle.py
.eggs/pycodestyle-2.8.0-py3.10.egg/EGG-INFO/LICENSE
.eggs/pyflakes-2.4.0-py3.10.egg/EGG-INFO/LICENSE
.eggs/pyflakes-2.4.0-py3.10.egg/pyflakes/__init__.py
.eggs/pyflakes-2.4.0-py3.10.egg/pyflakes/__main__.py
.eggs/pyflakes-2.4.0-py3.10.egg/pyflakes/api.py
.eggs/pyflakes-2.4.0-py3.10.egg/pyflakes/checker.py
.eggs/pyflakes-2.4.0-py3.10.egg/pyflakes/messages.py
.eggs/pyflakes-2.4.0-py3.10.egg/pyflakes/reporter.py
.eggs/pyflakes-2.4.0-py3.10.egg/pyflakes/scripts/__init__.py
coinpricli.egg-info/PKG-INFO
coinpricli.egg-info/SOURCES.txt
coinpricli.egg-info/dependency_links.txt
coinpricli.egg-info/entry_points.txt
coinpricli.egg-info/requires.txt
coinpricli.egg-info/top_level.txt