Metadata-Version: 2.1
Name: coinpricli
Version: 0.0.4
Summary: a package where you can easily monitor cryptocurrencies
Home-page: https://github.com/dumpsayamrat/coinpricli
Author: Sayamrat Kaewta
Author-email: sayamrat.kt@gmail.com
License: BSD
Keywords: cryptocurrency cli coin coicli
Platform: UNKNOWN
Classifier: License :: OSI Approved :: BSD License
Classifier: Programming Language :: Python :: 3.8
Classifier: Programming Language :: Python :: 3.9
Classifier: Programming Language :: Python :: 3.10
Classifier: Programming Language :: Python :: 3.11
License-File: LICENSE
